blockwise_parallel/__init__.py
blockwise_parallel/blockwise_paralle.py
blockwise_parallel/jax_v1.py
blockwise_parallel/test1.py
blockwise_parallel_transformer-0.3.2.dist-info/LICENSE
blockwise_parallel_transformer-0.3.2.dist-info/METADATA
blockwise_parallel_transformer-0.3.2.dist-info/WHEEL
blockwise_parallel_transformer-0.3.2.dist-info/top_level.txt
blockwise_parallel_transformer-0.3.2.dist-info/RECORD
