Metadata-Version: 2.1
Name: blockwise-parallel-transformer
Version: 0.3.2
Summary: Tree of Thoughts - Pytorch
Home-page: https://github.com/kyegomez/Blockwise-Parallel-Transformer
Author: Kye Gomez
Author-email: kye@apac.ai
License: MIT
Keywords: artificial intelligence,deep learning,optimizers,Prompt Engineering
Classifier: Development Status :: 4 - Beta
Classifier: Intended Audience :: Developers
Classifier: Topic :: Scientific/Engineering :: Artificial Intelligence
Classifier: License :: OSI Approved :: MIT License
Classifier: Programming Language :: Python :: 3.6
License-File: LICENSE
Requires-Dist: guidance
Requires-Dist: openai
Requires-Dist: transformers
